{ "commands": [
  { "hdr": "7E4", "rax": "7EC", "cmd": { "22": "4801" }, "freq": 2,
    "signals": [
      { "id": "FOC_SOC_STD", "path": "Battery", "fmt": { "len": 8, "max": 255, "div": 1.85, "unit": "percent" }, "name": "SOC (Standard 1.85)", "suggestedMetric": "stateOfCharge" },
      { "id": "FOC_SOC_ADJ", "path": "Battery", "fmt": { "len": 8, "max": 255, "div": 2.05, "unit": "percent" }, "name": "SOC (Adjusted 2.05)", "suggestedMetric": "stateOfCharge" },
      { "id": "FOC_SOC_LOW", "path": "Battery", "fmt": { "len": 8, "max": 255, "div": 2.25, "unit": "percent" }, "name": "SOC (Low-End 2.25)", "suggestedMetric": "stateOfCharge" },
      { "id": "FOC_CALC_RANGE", "path": "Trips", "fmt": { "len": 8, "max": 255, "div": 1.79, "unit": "miles" }, "name": "Est. Range (Heat OFF)", "suggestedMetric": "electricRange" },
      { "id": "FOC_CALC_RANGE_HEAT", "path": "Trips", "fmt": { "len": 8, "max": 255, "div": 2.3, "unit": "miles" }, "name": "Est. Range (Heat ON)", "suggestedMetric": "electricRange" },
      { "id": "FOC_CHRG_STATE", "path": "Battery", "fmt": { "len": 8, "max": 255, "map": { "0": { "val": "Not Charging", "desc": "Not Charging" }, "1": { "val": "Charging", "desc": "Charging" }, "2": { "val": "Complete", "desc": "Charge Complete" }, "3": { "val": "Fault", "desc": "Charging Fault" } } }, "name": "Charging State", "suggestedMetric": "isCharging" }
    ]
  },
  { "hdr": "7E4", "rax": "7EC", "cmd": { "22": "480D" }, "freq": 1,
    "signals": [
      { "id": "FOC_BATT_SOH", "path": "Battery", "fmt": { "len": 8, "max": 255, "div": 2.55, "unit": "percent" }, "name": "Battery Health (SOH)", "suggestedMetric": "stateOfHealth" }
    ]
  },
  { "hdr": "7E4", "rax": "7EC", "cmd": { "22": "D115" }, "freq": 5,
    "signals": [
      { "id": "FOC_BATT_VOLTS", "path": "Battery", "fmt": { "len": 16, "max": 65000, "div": 10, "unit": "volts" }, "name": "HV Battery Voltage", "suggestedMetric": "batteryVoltage" }
    ]
  },
  { "hdr": "7E4", "rax": "7EC", "cmd": { "22": "D101" }, "freq": 5,
    "signals": [
      { "id": "FOC_BATT_AMPS", "path": "Battery", "fmt": { "len": 16, "max": 65000, "min": -65000, "sign": true, "add": -32768, "div": 10, "unit": "amperes" }, "name": "HV Battery Current", "suggestedMetric": "batteryCurrent" }
    ]
  },
  { "hdr": "7E0", "rax": "7E8", "cmd": { "22": "F442" }, "freq": 1,
    "signals": [
      { "id": "FOC_12V_BATT", "path": "Battery", "fmt": { "len": 16, "max": 65535, "div": 1000, "unit": "volts" }, "name": "12V Battery Voltage", "suggestedMetric": "batteryVoltage" }
    ]
  },
  { "hdr": "7E0", "rax": "7E8", "cmd": { "22": "F446" }, "freq": 1,
    "signals": [
      { "id": "FOC_AMB_TEMP", "path": "Climate", "fmt": { "len": 8, "max": 255, "min": -40, "add": -40, "unit": "celsius" }, "name": "Ambient Temperature" }
    ]
  },
  { "hdr": "7E0", "rax": "7E8", "cmd": { "22": "1E12" }, "freq": 2,
    "signals": [
      { "id": "FOC_GEAR_POS", "path": "Movement", "fmt": { "len": 8, "max": 255, "unit": "scalar", "map": { "0": { "val": "P", "desc": "Park" }, "1": { "val": "R", "desc": "Reverse" }, "2": { "val": "N", "desc": "Neutral" }, "3": { "val": "D", "desc": "Drive" }, "4": { "val": "L", "desc": "Low" } } }, "name": "Gear Position" }
    ]
  },
  { "hdr": "7E0", "rax": "7E8", "cmd": { "22": "099B" }, "freq": 5,
    "signals": [
      { "id": "FOC_AC_STATE", "path": "Climate", "fmt": { "len": 8, "max": 1, "unit": "offon" }, "name": "A/C Compressor State" }
    ]
  },
  { "hdr": "7E0", "rax": "7E8", "cmd": { "22": "F40D" }, "freq": 10,
    "signals": [
      { "id": "FOC_VSS", "path": "Movement", "fmt": { "len": 8, "max": 255, "unit": "kilometersPerHour" }, "name": "Vehicle Speed", "suggestedMetric": "speed" }
    ]
  },
  { "hdr": "760", "rax": "768", "cmd": { "22": "2B00" }, "freq": 3,
    "signals": [
      { "id": "FOC_PARKING_BRAKE", "path": "Movement", "fmt": { "len": 1, "max": 1, "unit": "offon" }, "name": "Parking Brake" }
    ]
  },
  { "hdr": "760", "rax": "768", "cmd": { "22": "3201" }, "freq": 5,
    "signals": [
      { "id": "FOC_STEER_ANGLE", "path": "Movement", "fmt": { "len": 8, "max": 790, "min": -790, "mul": 6.25, "sign": true, "unit": "degrees" }, "name": "Steering Wheel Angle" }
    ]
  },
  { "hdr": "726", "rax": "72E", "cmd": { "22": "2813" }, "freq": 5,
    "signals": [
      { "id": "FOC_TP_FL", "path": "Tires", "fmt": { "len": 16, "max": 3276, "div": 20, "unit": "psi" }, "name": "Front Left Pressure", "suggestedMetric": "frontLeftTirePressure" }
    ]
  },
  { "hdr": "726", "rax": "72E", "cmd": { "22": "2814" }, "freq": 5,
    "signals": [
      { "id": "FOC_TP_FR", "path": "Tires", "fmt": { "len": 16, "max": 3276, "div": 20, "unit": "psi" }, "name": "Front Right Pressure", "suggestedMetric": "frontRightTirePressure" }
    ]
  },
  { "hdr": "726", "rax": "72E", "cmd": { "22": "2815" }, "freq": 5,
    "signals": [
      { "id": "FOC_TP_RR", "path": "Tires", "fmt": { "len": 16, "max": 3276, "div": 20, "unit": "psi" }, "name": "Rear Right Pressure", "suggestedMetric": "rearRightTirePressure" }
    ]
  },
  { "hdr": "726", "rax": "72E", "cmd": { "22": "2816" }, "freq": 5,
    "signals": [
      { "id": "FOC_TP_RL", "path": "Tires", "fmt": { "len": 16, "max": 3276, "div": 20, "unit": "psi" }, "name": "Rear Left Pressure", "suggestedMetric": "rearLeftTirePressure" }
    ]
  },
  { "hdr": "726", "rax": "72E", "cmd": { "22": "C150" }, "freq": 3,
    "signals": [
      { "id": "FOC_TRUNK_OPEN", "path": "Doors", "fmt": { "bix": 11, "len": 1, "max": 1, "unit": "noyes" }, "name": "Trunk Ajar" },
      { "id": "FOC_RRD_OPEN", "path": "Doors", "fmt": { "bix": 12, "len": 1, "max": 1, "unit": "noyes" }, "name": "Rear Right Door Ajar" },
      { "id": "FOC_RLD_OPEN", "path": "Doors", "fmt": { "bix": 13, "len": 1, "max": 1, "unit": "noyes" }, "name": "Rear Left Door Ajar" },
      { "id": "FOC_DRIVER_DOOR_OPEN", "path": "Doors", "fmt": { "bix": 16, "len": 1, "max": 1, "unit": "noyes" }, "name": "Driver Door Ajar" },
      { "id": "FOC_PASSENGER_DOOR_OPEN", "path": "Doors", "fmt": { "bix": 17, "len": 1, "max": 1, "unit": "noyes" }, "name": "Passenger Door Ajar" }
    ]
  },
  { "hdr": "726", "rax": "72E", "cmd": { "22": "C154" }, "freq": 3,
    "signals": [
      { "id": "FOC_HOOD_OPEN", "path": "Doors", "fmt": { "len": 1, "max": 1, "unit": "noyes" }, "name": "Hood Ajar" }
    ]
  },
  { "hdr": "726", "rax": "72E", "cmd": { "22": "407E" }, "freq": 1,
    "signals": [
      { "id": "FOC_EXT_LIGHTS", "path": "Lights", "fmt": { "len": 8, "max": 255, "unit": "scalar", "map": { "216": { "val": "ON", "desc": "Lights On" }, "0": { "val": "OFF", "desc": "Lights Off" } } }, "name": "Exterior Lights" }
    ]
  },
  { "hdr": "726", "rax": "72E", "cmd": { "22": "7151" }, "freq": 4,
    "signals": [
      { "id": "FOC_HIGHBEAM", "path": "Lights", "fmt": { "len": 16, "max": 2, "unit": "offon" }, "name": "Highbeam Status" }
    ]
  },
  { "hdr": "720", "rax": "728", "cmd": { "22": "DD01" }, "freq": 1,
    "signals": [
      { "id": "FOC_ODO", "path": "Trips", "fmt": { "len": 24, "max": 16777215, "div": 10, "unit": "kilometers" }, "name": "Odometer", "suggestedMetric": "odometer" }
    ]
  },
  { "hdr": "720", "rax": "728", "cmd": { "22": "61A5" }, "freq": 10,
    "signals": [
      { "id": "FOC_TPMS_WARN", "path": "Tires", "fmt": { "bix": 2, "len": 1, "max": 1, "unit": "offon" }, "name": "Tire Pressure Warning" }
    ]
  }
]}
